README.rst
setup.cfg
setup.py
./__init__.py
./carrier.py
./carrier.xml
./sale.py
./sale.xml
./shipment.py
./shipment.xml
./tryton.cfg
./tests/__init__.py
./tests/test_shipment.py
./tests/test_views_depends.py
./view/carrier_form.xml
./view/sale_view_form.xml
./view/shipment_form.xml
./view/shipping_gls_config_form.xml
fio_shipping_gls.egg-info/PKG-INFO
fio_shipping_gls.egg-info/SOURCES.txt
fio_shipping_gls.egg-info/dependency_links.txt
fio_shipping_gls.egg-info/entry_points.txt
fio_shipping_gls.egg-info/not-zip-safe
fio_shipping_gls.egg-info/requires.txt
fio_shipping_gls.egg-info/top_level.txt